szurubooru_client-0.6.2.dist-info/METADATA
szurubooru_client-0.6.2.dist-info/WHEEL
szurubooru_client/models.py
szurubooru_client/__init__.py
szurubooru_client/tokens.py
szurubooru_client/szurubooru_client.pypy37-pp73-aarch64-linux-gnu.so
szurubooru_client-0.6.2.dist-info/RECORD
