Metadata-Version: 2.3
Name: szurubooru_client
Version: 0.6.2
Classifier: Programming Language :: Rust
Classifier: Programming Language :: Python :: Implementation :: CPython
Classifier: Programming Language :: Python :: Implementation :: PyPy
Classifier: Development Status :: 4 - Beta
Classifier: Environment :: Console
Classifier: Environment :: Web Environment
Classifier: Intended Audience :: End Users/Desktop
Classifier: Operating System :: Microsoft :: Windows
Classifier: Operating System :: MacOS :: MacOS X
Classifier: Operating System :: POSIX
Classifier: Topic :: Multimedia :: Graphics
Summary: A wrapper around the Szurubooru API, including type-safe Query and Sort tokens
Keywords: image_host,szurubooru,booru
Author: Scott Lyons <scottalyons@gmail.com>
Author-email: Scott Lyons <scottalyons@gmail.com>
License: MIT
Requires-Python: >=3.7
Project-URL: Source Code, https://github.com/slyons/szurubooru-client
